fastdfe/__init__.py
fastdfe/abstract_inference.py
fastdfe/annotation.py
fastdfe/base_inference.py
fastdfe/bootstrap.py
fastdfe/config.py
fastdfe/discretization.py
fastdfe/filtration.py
fastdfe/io_handlers.py
fastdfe/joint_inference.py
fastdfe/json_handlers.py
fastdfe/likelihood.py
fastdfe/optimization.py
fastdfe/parametrization.py
fastdfe/parser.py
fastdfe/polydfe.py
fastdfe/polydfe_utils.py
fastdfe/settings.py
fastdfe/simulation.py
fastdfe/spectrum.py
fastdfe/utils.py
fastdfe/visualization.py
fastdfe-1.2.1.dist-info/METADATA
fastdfe-1.2.1.dist-info/WHEEL
fastdfe-1.2.1.dist-info/licenses/LICENSE
fastdfe-1.2.1.dist-info/RECORD
