Metadata-Version: 2.4
Name: fastdfe
Version: 1.2.1
Summary: Fast and flexible inference of the distribution of fitness effects (DFE), VCF-SFS parsing with ancestral allele and site-degeneracy annotation.
License: MIT
License-File: LICENSE
Author: Sendrowski
Author-email: sendrowski.janek@gmail.com
Requires-Python: >=3.10.0,<3.13
Classifier: License :: OSI Approved :: MIT License
Classifier: Programming Language :: Python :: 3
Classifier: Programming Language :: Python :: 3.10
Classifier: Programming Language :: Python :: 3.11
Classifier: Programming Language :: Python :: 3.12
Provides-Extra: vcf
Requires-Dist: biopython (>=1.80,<1.82)
Requires-Dist: cyvcf2 (>=0.31.0,<0.32.0) ; extra == "vcf"
Requires-Dist: jsonpickle (>=3.0.0,<4.0.0)
Requires-Dist: matplotlib (>=3.7.0,<4.0.0)
Requires-Dist: mpmath (>=1.3.0,<2.0.0)
Requires-Dist: multiprocess (>=0.70.12,<0.71.0)
Requires-Dist: numpy (>=1.24.0,<2.0.0)
Requires-Dist: pandas (>=2.0.0,<3.0.0)
Requires-Dist: pyyaml (>=6.0,<7.0)
Requires-Dist: requests (>=2.28)
Requires-Dist: scipy (>=1.10.1,<2.0.0)
Requires-Dist: seaborn (>=0.13.0,<0.14.0)
Requires-Dist: tqdm (>=4.60.0,<5.0.0)
Requires-Dist: typing-extensions (>=4.5.0,<5.0.0)
